cit_pydata/__init__.py
cit_pydata/aws/__init__.py
cit_pydata/aws/api.py
cit_pydata/box/__init__.py
cit_pydata/box/api.py
cit_pydata/joblog/__init__.py
cit_pydata/joblog/api.py
cit_pydata/marketo/__init__.py
cit_pydata/marketo/api.py
cit_pydata/salesforce/__init__.py
cit_pydata/salesforce/api.py
cit_pydata/sfsync/__init__.py
cit_pydata/sfsync/api.py
cit_pydata/sftp/__init__.py
cit_pydata/sftp/api.py
cit_pydata/sql/__init__.py
cit_pydata/sql/api.py
cit_pydata/util/__init__.py
cit_pydata/util/api.py
cit_pydata-0.0.1.dev10.dist-info/licenses/LICENSE
cit_pydata-0.0.1.dev10.dist-info/METADATA
cit_pydata-0.0.1.dev10.dist-info/WHEEL
cit_pydata-0.0.1.dev10.dist-info/top_level.txt
cit_pydata-0.0.1.dev10.dist-info/RECORD
