Metadata-Version: 2.4
Name: cit-pydata
Version: 0.0.1.dev10
Summary: Python clients for commonly used api services including Salesforce, SQL, Marketo, Box, SFSync*, and JobLog*
Author-email: Dionis Wang <dwang@eab.com>, Andrew Fitch <afitch@eab.com>
Project-URL: Homepage, https://github.com/EAB-IT-DEV/cit-pydata
Project-URL: Issues, https://github.com/EAB-IT-DEV/cit-pydata/issues
Classifier: Programming Language :: Python :: 3
Classifier: License :: OSI Approved :: MIT License
Classifier: Operating System :: POSIX :: Linux
Requires-Python: >=3.12
License-File: LICENSE
Provides-Extra: aws
Requires-Dist: aws-lambda-powertools; extra == "aws"
Requires-Dist: boto3; extra == "aws"
Provides-Extra: box
Requires-Dist: boxsdk; extra == "box"
Provides-Extra: joblog
Requires-Dist: marketorestpython; extra == "joblog"
Provides-Extra: salesforce
Requires-Dist: simple_salesforce; extra == "salesforce"
Requires-Dist: pyforce; extra == "salesforce"
Provides-Extra: sftp
Requires-Dist: paramiko; extra == "sftp"
Provides-Extra: sql
Requires-Dist: SQLAlchemy<2.0; extra == "sql"
Requires-Dist: numpy; extra == "sql"
Requires-Dist: pandas; extra == "sql"
Provides-Extra: sql-pyodbc
Requires-Dist: SQLAlchemy<2.0; extra == "sql-pyodbc"
Requires-Dist: pyodbc; extra == "sql-pyodbc"
Requires-Dist: numpy; extra == "sql-pyodbc"
Requires-Dist: pandas; extra == "sql-pyodbc"
Provides-Extra: sql-pymssql
Requires-Dist: SQLAlchemy<2.0; extra == "sql-pymssql"
Requires-Dist: pymssql; extra == "sql-pymssql"
Requires-Dist: numpy; extra == "sql-pymssql"
Requires-Dist: pandas; extra == "sql-pymssql"
Provides-Extra: sql-psycopg2
Requires-Dist: SQLAlchemy<2.0; extra == "sql-psycopg2"
Requires-Dist: psycopg2-binary; extra == "sql-psycopg2"
Requires-Dist: numpy; extra == "sql-psycopg2"
Requires-Dist: pandas; extra == "sql-psycopg2"
Provides-Extra: sql-mssql
Requires-Dist: SQLAlchemy<2.0; extra == "sql-mssql"
Requires-Dist: pymssql; extra == "sql-mssql"
Requires-Dist: numpy; extra == "sql-mssql"
Requires-Dist: pandas; extra == "sql-mssql"
Provides-Extra: sql-postgres
Requires-Dist: SQLAlchemy<2.0; extra == "sql-postgres"
Requires-Dist: psycopg2-binary; extra == "sql-postgres"
Requires-Dist: numpy; extra == "sql-postgres"
Requires-Dist: pandas; extra == "sql-postgres"
Provides-Extra: local
Requires-Dist: python-dotenv; extra == "local"
Provides-Extra: all
Requires-Dist: aws-lambda-powertools; extra == "all"
Requires-Dist: pandas; extra == "all"
Requires-Dist: boxsdk; extra == "all"
Requires-Dist: marketorestpython; extra == "all"
Requires-Dist: simple_salesforce; extra == "all"
Requires-Dist: pyforce; extra == "all"
Requires-Dist: paramiko; extra == "all"
Requires-Dist: SQLAlchemy<2.0; extra == "all"
Requires-Dist: pyodbc; extra == "all"
Requires-Dist: pymssql; extra == "all"
Requires-Dist: numpy; extra == "all"
Requires-Dist: pandas; extra == "all"
Requires-Dist: psycopg2-binary; extra == "all"
Requires-Dist: python-dotenv; extra == "all"
Requires-Dist: boto3; extra == "all"
Dynamic: license-file
